zillow/__init__.py
zillow/zillow.py
zillow/models/__init__.py
zillow/models/address.py
zillow/models/listing.py
zillow/models/listing_area_size.py
zillow/models/listing_features.py
zillow/models/listing_image.py
zillow/models/listing_video.py
zillow/models/price_history_entry.py
zillow/models/region.py
zillow/models/search_result_listing.py
zillow/models/enums/__init__.py
zillow/models/enums/listing_asset_type.py
zillow/models/enums/listing_sort_type.py
zillow-0.0.10.dist-info/METADATA
zillow-0.0.10.dist-info/WHEEL
zillow-0.0.10.dist-info/top_level.txt
zillow-0.0.10.dist-info/RECORD
