Metadata-Version: 2.1
Name: zillow
Version: 0.0.10
Summary: zillow
Home-page: https://github.com/kopnt/zillow
Author: Kristof
License: UNKNOWN
Platform: UNKNOWN
Classifier: Programming Language :: Python :: 3
Classifier: License :: OSI Approved :: MIT License
Classifier: Operating System :: OS Independent
Requires-Python: >=3.5
Requires-Dist: jsoncodable (>=0.0.12)
Requires-Dist: kffmpeg (>=0.2.39)
Requires-Dist: ksimpleapi (>=0.0.38)
Requires-Dist: kstopit (>=0.0.10)
Requires-Dist: m3u8 (>=0.8.0)
Requires-Dist: randomua (>=0.0.7)
Requires-Dist: simple-multiprocessing (>=0.0.13)
